doc_dict/__init__.py
doc_dict/datastructures.py
doc_dict/factory.py
tests/__init__.py
tests/test_factory.py
doc_dict-0.0.3.dist-info/METADATA
doc_dict-0.0.3.dist-info/WHEEL
doc_dict-0.0.3.dist-info/top_level.txt
doc_dict-0.0.3.dist-info/RECORD
