Metadata-Version: 2.1
Name: doc-dict
Version: 0.0.3
Summary: Dict with documentation _-_
Home-page: https://github.com/Kel0/doc_dict
Author: Example Author
Author-email: rickeyfsimple@example.com
License: UNKNOWN
Platform: UNKNOWN
Classifier: Programming Language :: Python :: 3
Requires-Python: >=3.7
